walt/__init__.py
walt/common/__init__.py
walt/common/api.py
walt/common/apilink.py
walt/common/busybox_init.py
walt/common/config.py
walt/common/constants.py
walt/common/evloop.py
walt/common/fakeipxe.py
walt/common/fifo.py
walt/common/formatting.py
walt/common/io.py
walt/common/logs.py
walt/common/netsetup.py
walt/common/reusable.py
walt/common/service.py
walt/common/settings.py
walt/common/setup.py
walt/common/systemd.py
walt/common/tcp.py
walt/common/term.py
walt/common/tools.py
walt/common/tty.py
walt/common/udp.py
walt/common/unix.py
walt/common/version.py
walt/common/crypto/__init__.py
walt/common/crypto/blowfish.py
walt/common/crypto/dh.py
walt/common/devices/__init__.py
walt/common/devices/registry.py
walt/common/devices/switches/__init__.py
walt/common/devices/switches/netgear.py
walt_common-10.0.dist-info/METADATA
walt_common-10.0.dist-info/WHEEL
walt_common-10.0.dist-info/top_level.txt
walt_common-10.0.dist-info/RECORD
